odoo/addons/fieldservice_sale_sign/README.rst
odoo/addons/fieldservice_sale_sign/__init__.py
odoo/addons/fieldservice_sale_sign/__manifest__.py
odoo/addons/fieldservice_sale_sign/i18n/es.po
odoo/addons/fieldservice_sale_sign/i18n/fieldservice_sale_sign.pot
odoo/addons/fieldservice_sale_sign/models/__init__.py
odoo/addons/fieldservice_sale_sign/models/fsm_order.py
odoo/addons/fieldservice_sale_sign/readme/CONTRIBUTORS.rst
odoo/addons/fieldservice_sale_sign/readme/DESCRIPTION.rst
odoo/addons/fieldservice_sale_sign/readme/USAGE.rst
odoo/addons/fieldservice_sale_sign/security/ir.model.access.csv
odoo/addons/fieldservice_sale_sign/static/icon.png
odoo/addons/fieldservice_sale_sign/static/description/icon.png
odoo/addons/fieldservice_sale_sign/static/description/index.html
odoo/addons/fieldservice_sale_sign/tests/__init__.py
odoo/addons/fieldservice_sale_sign/tests/test_fieldservice_sale_sign.py
odoo/addons/fieldservice_sale_sign/tests/static/test_signature.png
odoo/addons/fieldservice_sale_sign/views/fsm_order.xml
odoo/addons/fieldservice_sale_sign/wizard/__init__.py
odoo/addons/fieldservice_sale_sign/wizard/fsm_order_signature_wizard.py
odoo/addons/fieldservice_sale_sign/wizard/fsm_order_signature_wizard.xml
odoo_addon_fieldservice_sale_sign-15.0.1.0.0.2.dist-info/METADATA
odoo_addon_fieldservice_sale_sign-15.0.1.0.0.2.dist-info/WHEEL
odoo_addon_fieldservice_sale_sign-15.0.1.0.0.2.dist-info/top_level.txt
odoo_addon_fieldservice_sale_sign-15.0.1.0.0.2.dist-info/RECORD
